{"type":"FeatureCollection","features":[{"type":"Feature","properties":{"Category":"university","color":"","Description":"Iowa State University "},"geometry":{"type":"Point","coordinates":[42.03,-93.61]}},{"type":"Feature","properties":{"Category":"university","color":"","Description":"University of Iowa"},"geometry":{"type":"Point","coordinates":[41.66,-91.534]}},{"type":"Feature","properties":{"Category":"university","color":"","name":"Drake University "},"geometry":{"type":"Point","coordinates":[41.5,-93.543056]}},{"type":"Feature","properties":{"Category":"landmarks","color":"","Description":"Amana Colonies,Iowa"},"geometry":{"type":"Point","coordinates":[41.7,-91.9]}},{"type":"Feature","properties":{"Category":"landmarks","color":"","Description":"Dubuque County Jail "},"geometry":{"type":"Point","coordinates":[42.5,-90.705833]}},{"type":"Feature","properties":{"Category":"landmarks","color":"","Description":"Sergeant Floyd Monument "},"geometry":{"type":"Point","coordinates":[42.526667,-96.30416]}}]}
