{"type":"FeatureCollection","features":[{"type":"Feature","properties":{"landuse":"university","color":"","name":"Iowa State University "},"geometry":{"type":"Point","coordinates":[-93.61,42.03]}},{"type":"Feature","properties":{"landuse":"university","color":"","name":"University of Iowa"},"geometry":{"type":"Point","coordinates":[-91.534,41.66]}},{"type":"Feature","properties":{"landuse":"university","color":"","name":"Drake University "},"geometry":{"type":"Point","coordinates":[-93.543056,41.5]}},{"type":"Feature","properties":{"landuse":"landmarks","color":"","name":"Amana Colonies,Iowa"},"geometry":{"type":"Point","coordinates":[-91.9,41.7]}},{"type":"Feature","properties":{"landuse":"landmarks","color":"","name":"Dubuque County Jail "},"geometry":{"type":"Point","coordinates":[-90.705833,42.5]}},{"type":"Feature","properties":{"landuse":"landmarks","color":"","name":"Sergeant Floyd Monument "},"geometry":{"type":"Point","coordinates":[-96.30416,42.526667]}}]}
