{
  "type": "FeatureCollection",
  "features": [
    {
      "type": "Feature",
      "properties": {
        "marker-color": "#7e7e7e",
        "marker-size": "medium",
        "landuse": "university",
        "name": "Iowa State University "
      },
      "geometry": {
        "type": "Point",
        "coordinates": [
         42.03,
        -93.61
        ]
      }
    },
    {
      "type": "Feature",
      "properties": {
        "marker-color": "#7e7e7e",
        "marker-size": "medium",
        "landuse": "university",
        "name": "University of Iowa"
      },
      "geometry": {
        "type": "Point",
        "coordinates": [
          41.66, -91.534
        ]
      }
    },
    {
      "type": "Feature",
      "properties": {
        "marker-color": "#7e7e7e",
        "marker-size": "medium",
        "landuse": "university",
        "name": "Drake University "
      },
      "geometry": {
        "type": "Point",
        "coordinates": [
          41.5, 
         -93.543056
        ]
      }
    },
    {
      "type": "Feature",
      "properties": {
        "marker-color": "#7e7e7e",
        "marker-size": "medium",
        "landuse": "landmarks",
        "name": "Amana Colonies,Iowa"
      },
      "geometry": {
        "type": "Point",
        "coordinates": [
          41.7, 
          -91.9
        ]
      }
    },
    {
      "type": "Feature",
      "properties": {
        "marker-color": "#7e7e7e",
        "marker-size": "medium",
        "landuse": "landmarks",
        "name": "Dubuque County Jail "
      },
      "geometry": {
        "type": "Point",
        "coordinates": [
          42.5,
          -90.705833
        ]
      }
    },
   {
      "type": "Feature",
      "properties": {
        "marker-color": "#7e7e7e",
        "marker-size": "medium",
        "landuse": "landmarks",
        "name": "Sergeant Floyd Monument "
      },
      "geometry": {
        "type": "Point",
        "coordinates": [
          42.526667,
          -96.30416
        ]
      }
    }
    
